toolbelt/__init__.py
toolbelt/cli.py
toolbelt/flask.py
toolbelt/grpc.py
toolbelt/gunicorn.py
toolbelt/logging.py
toolbelt/py.typed
toolbelt/sqlalchemy/__init__.py
toolbelt/sqlalchemy/process_safe_session.py
toolbelt/sqlalchemy/types.py
tool_belt-0.0.2.dist-info/AUTHORS.md
tool_belt-0.0.2.dist-info/LICENSE
tool_belt-0.0.2.dist-info/METADATA
tool_belt-0.0.2.dist-info/WHEEL
tool_belt-0.0.2.dist-info/top_level.txt
tool_belt-0.0.2.dist-info/zip-safe
tool_belt-0.0.2.dist-info/RECORD
