Metadata-Version: 2.1
Name: tool-belt
Version: 0.0.2
Summary: A set of utility modules that helps you create web services faster.
Home-page: https://github.com/mmohaveri/python-tool-belt
Author: Mahdi Mohaveri
Author-email: mmohaveri@gmail.com
License: MIT License
Keywords: web-service,toolkit,toolbelt,logging,grpc,flask,gunicorn,cli
Platform: UNKNOWN
Classifier: Development Status :: 3 - Alpha
Classifier: Intended Audience :: Developers
Classifier: License :: OSI Approved :: MIT License
Classifier: Operating System :: OS Independent
Classifier: Operating System :: Unix
Classifier: Operating System :: POSIX
Classifier: Operating System :: Microsoft :: Windows
Classifier: Programming Language :: Python
Classifier: Programming Language :: Python :: 3
Classifier: Programming Language :: Python :: 3 :: Only
Classifier: Programming Language :: Python :: 3.5
Classifier: Programming Language :: Python :: 3.6
Classifier: Programming Language :: Python :: 3.7
Classifier: Programming Language :: Python :: 3.8
Classifier: Programming Language :: Python :: Implementation :: PyPy
Classifier: Topic :: Software Development
Classifier: Topic :: Utilities
Classifier: Typing :: Typed
Requires-Python: >=3.5
Provides-Extra: cli
Provides-Extra: flask
Requires-Dist: Flask (>=1.1.1) ; extra == 'flask'
Provides-Extra: grpc
Requires-Dist: grpcio (>=1.17.1) ; extra == 'grpc'
Requires-Dist: googleapis-common-protos (>=1.5.5) ; extra == 'grpc'
Provides-Extra: gunicorn
Requires-Dist: gunicorn (>=20.0.4) ; extra == 'gunicorn'
Provides-Extra: logging
Provides-Extra: sqlalchemy
Requires-Dist: SQLAlchemy (>=1.3.15) ; extra == 'sqlalchemy'
